helper/__init__.py
helper/ddl.py
helper/etl.py
helper/hello.py
helper/helm.py
helper/pack.py
helper/base/__init__.py
helper/base/logger.py
helper/base/writer.py
helper/plugin/__init__.py
helper/plugin/etl_base.py
helper/plugin/etl_postgre.py
work_helper-0.1.5.dist-info/entry_points.txt
work_helper-0.1.5.dist-info/LICENSE
work_helper-0.1.5.dist-info/WHEEL
work_helper-0.1.5.dist-info/METADATA
work_helper-0.1.5.dist-info/RECORD
