Metadata-Version: 2.1
Name: work-helper
Version: 0.1.5
Summary: helper tool
Author-email: fengbing <bing.feng@iquantex.com>
Requires-Python: >=3.6
Classifier: License :: OSI Approved :: MIT License
Requires-Dist: openpyxl >=3.0
